{"problem_id":{"dataset":6,"instance":6,"case":3},"methods":{"decreasing time":[{"solution":[false,true,true,true,false,false,true,false,false,true,true,true,true,false,false,true,false,false,false,true,true,true,false,true,false,true,true,true,true,false,false,false,true,true,false,false,true,false,true,true,false,false,false,true,false,true,false,false,false,false,false,false,false,true,false,false,true,true,true,false,true,false,false,true,true,true,true,false,true,true,false,true,true,false,false,false,false,false,true,false,true,true,false,true,true,false,true,false,false,false,true,false,true,false,false,true,false,false,true,false,false,true,false,true,false,true,false,false,false,false,false,true,true,false,true,false,true,true,false,false,false,true,true,true,true,true,true,true,false,false,false,true,false,true,true,false,true,true,false,false,true,false,false,true,true,true,true,true,false,true,true,true,true,false,true,true,true,true,false,false,false,true,false,false,false,true,false,true,true,true,true,true,true,false,false,true,false,false,true,true,false,true,true,true,true,true,true,true,false,false,true,true,false,true,false,true,false,true,true,false,false,true,true,false,true,false,false,true,false,false,false,true,false,true,false,false,true,true,true,true,false,false,true,true,false,false,true,true,true,false,false,true,true,false,true,false,false,true,false,false,false,true,false,true,true,true,false,false,false,true,true,false,false,true,true,true,false,true,true,false,true,true,false,true,false,false,false,true,true,true,false,false,true,false,true,true,true,true,true,false,false,false,true,true,true,false,true,true,true,false,true,true,true,true,false,true,true,true,true,false,false,false,true,true,true,false,true,false,true,true,true,true,false,false,true,true,true,false,false,true,true,true,true,true,true,true,false,true,false,true,false,false,true,true,true,true,false,false,false,true,true,false,false,false,true,false,true,true,false,true,false,true,true,false,true,false,true,true,true,false,false,false,false,false,false,false,false,false,true,false,true,false,false,false,false,false,true,true,false,false,false,true,false,false,true,false,true,false,true,false,true,true,true,false,false,true,false,false,true,true,false,false,false,true,true,true,true,true,true,false,false,false,false,false,false,true,true,true,true,false,false,true,false,false,true,true,false,true,true,true,true,false,false,true,false,true,true,false,true,false,true,false,false,false,false,false,false,false,false,false,false,true,true,true,false,false,true,true,true,true,false,true,true,true,false,true,false,false,false,false,false,false,false,true,false,false,false,true,true,false,false,true,false,false,true,false,false,true,true,true,false,true,true,false,true,true,true,false,true,true],"repr":"301/601/753/174/120/105/838/323/732/987/504/378/258/474/835/610/412/602/258/765/374/488/169/374/457/845/740/225/153/561/158/677/527/137/827/377/3/778/447/602/65/17/428/887/768/296/312/101/436/358","tolerance":0.005,"cplex_objective":182695.0,"objective":182695,"infeasibility":0,"elapsed_time":0.4119999408721924,"solution_status":"FEASIBLE_POINT","termination_status":"OPTIMAL","gap":0.0033338525430134415}],"even time":[{"solution":[false,true,true,true,false,false,true,false,false,true,true,true,true,false,false,true,false,false,false,true,true,true,false,true,false,true,true,true,true,false,false,false,true,true,false,false,true,false,true,true,false,false,false,true,false,true,false,false,false,false,false,false,false,true,false,false,true,true,true,false,true,false,false,true,true,true,true,false,true,true,false,true,true,false,false,false,false,false,true,false,true,true,false,true,true,false,true,false,false,false,true,false,true,false,false,true,false,false,true,false,false,true,false,true,false,true,false,false,false,false,false,true,true,false,true,false,true,true,false,false,false,true,true,true,true,true,true,true,false,false,false,true,false,true,true,false,true,true,false,false,true,false,false,true,true,true,true,true,false,true,true,true,true,false,true,true,true,true,false,false,false,true,false,false,false,true,false,true,true,true,true,true,true,false,false,true,false,false,true,true,false,true,true,true,true,true,true,true,false,false,true,true,false,true,false,true,false,true,true,false,false,true,true,false,true,false,false,true,false,false,false,true,false,true,false,false,true,true,true,true,false,false,true,true,false,false,true,true,true,false,false,true,true,false,true,false,false,true,false,false,false,true,false,true,true,true,false,false,false,true,true,false,false,true,true,true,false,true,true,false,true,true,false,true,false,false,false,true,true,true,false,false,true,false,true,true,true,true,true,false,false,false,true,true,true,false,true,true,true,false,true,true,true,true,false,true,true,true,true,false,false,false,true,true,true,false,true,false,true,true,true,true,false,false,true,true,true,false,false,true,true,true,true,true,true,true,false,true,false,true,false,false,true,true,true,true,false,false,false,true,true,false,false,false,true,false,true,true,false,true,false,true,true,false,true,false,true,true,true,false,false,false,false,false,false,false,false,false,true,false,true,false,false,false,false,false,true,true,false,false,false,true,false,false,true,false,true,false,true,false,true,true,true,false,false,true,false,false,true,true,false,false,false,true,true,true,true,true,true,false,false,false,false,false,false,true,true,true,true,false,false,true,false,false,true,true,false,true,true,true,true,false,false,true,false,true,true,false,true,false,true,false,false,false,false,false,false,false,false,false,false,true,true,true,false,false,true,true,true,true,false,true,true,true,false,true,false,false,false,false,false,false,false,true,false,false,false,true,true,false,false,true,false,false,true,false,false,true,true,true,false,true,true,false,true,true,true,false,true,true],"repr":"301/601/753/174/120/105/838/323/732/987/504/378/258/474/835/610/412/602/258/765/374/488/169/374/457/845/740/225/153/561/158/677/527/137/827/377/3/778/447/602/65/17/428/887/768/296/312/101/436/358","tolerance":0.005,"cplex_objective":182695.0,"objective":182695,"infeasibility":0,"elapsed_time":0.4160001277923584,"solution_status":"FEASIBLE_POINT","termination_status":"OPTIMAL","gap":0.0033338525430134415}],"increasing time":[{"solution":[false,true,true,true,false,false,true,false,false,true,true,true,true,false,false,true,false,false,false,true,true,true,false,true,false,true,true,true,true,false,false,false,true,true,false,false,true,false,true,true,false,false,false,true,false,true,false,false,false,false,false,false,false,true,false,false,true,true,true,false,true,false,false,true,true,true,true,false,true,true,false,true,true,false,false,false,false,false,true,false,true,true,false,true,true,false,true,false,false,false,true,false,true,false,false,true,false,false,true,false,false,true,false,true,false,true,false,false,false,false,false,true,true,false,true,false,true,true,false,false,false,true,true,true,true,true,true,true,false,false,false,true,false,true,true,false,true,true,false,false,true,false,false,true,true,true,true,true,false,true,true,true,true,false,true,true,true,true,false,false,false,true,false,false,false,true,false,true,true,true,true,true,true,false,false,true,false,false,true,true,false,true,true,true,true,true,true,true,false,false,true,true,false,true,false,true,false,true,true,false,false,true,true,false,true,false,false,true,false,false,false,true,false,true,false,false,true,true,true,true,false,false,true,true,false,false,true,true,true,false,false,true,true,false,true,false,false,true,false,false,false,true,false,true,true,true,false,false,false,true,true,false,false,true,true,true,false,true,true,false,true,true,false,true,false,false,false,true,true,true,false,false,true,false,true,true,true,true,true,false,false,false,true,true,true,false,true,true,true,false,true,true,true,true,false,true,true,true,true,false,false,false,true,true,true,false,true,false,true,true,true,true,false,false,true,true,true,false,false,true,true,true,true,true,true,true,false,true,false,true,false,false,true,true,true,true,false,false,false,true,true,false,false,false,true,false,true,true,false,true,false,true,true,false,true,false,true,true,true,false,false,false,false,false,false,false,false,false,true,false,true,false,false,false,false,false,true,true,false,false,false,true,false,false,true,false,true,false,true,false,true,true,true,false,false,true,false,false,true,true,false,false,false,true,true,true,true,true,true,false,false,false,false,false,false,true,true,true,true,false,false,true,false,false,true,true,false,true,true,true,true,false,false,true,false,true,true,false,true,false,true,false,false,false,false,false,false,false,false,false,false,true,true,true,false,false,true,true,true,true,false,true,true,true,false,true,false,false,false,false,false,false,false,true,false,false,false,true,true,false,false,true,false,false,true,false,false,true,true,true,false,true,true,false,true,true,true,false,true,true],"repr":"301/601/753/174/120/105/838/323/732/987/504/378/258/474/835/610/412/602/258/765/374/488/169/374/457/845/740/225/153/561/158/677/527/137/827/377/3/778/447/602/65/17/428/887/768/296/312/101/436/358","tolerance":0.005,"cplex_objective":182695.0,"objective":182695,"infeasibility":0,"elapsed_time":0.40400004386901855,"solution_status":"FEASIBLE_POINT","termination_status":"OPTIMAL","gap":0.0033338525430134415}],"one tolerance":[{"solution":[false,true,true,true,false,false,true,false,false,true,true,true,true,false,false,true,false,false,false,true,true,true,false,true,false,true,true,true,true,false,false,false,true,true,false,false,true,false,true,true,false,false,false,true,false,true,false,false,false,false,false,false,false,true,false,false,true,true,true,false,true,false,false,true,true,true,true,false,true,true,false,true,true,false,false,false,false,false,true,false,true,true,false,true,true,false,true,false,false,false,true,false,true,false,false,true,false,false,true,false,false,true,false,true,false,true,false,false,false,false,false,true,true,false,true,false,true,true,false,false,false,true,true,true,true,true,true,true,false,false,false,true,false,true,true,false,true,true,false,false,true,false,false,true,true,true,true,true,false,true,true,true,true,false,true,true,true,true,false,false,false,true,false,false,false,true,false,true,true,true,true,true,true,false,false,true,false,false,true,true,false,true,true,true,true,true,true,true,false,false,true,true,false,true,false,true,false,true,true,false,false,true,true,false,true,false,false,true,false,false,false,true,false,true,false,false,true,true,true,true,false,false,true,true,false,false,true,true,true,false,false,true,true,false,true,false,false,true,false,false,false,true,false,true,true,true,false,false,false,true,true,false,false,true,true,true,false,true,true,false,true,true,false,true,false,false,false,true,true,true,false,false,true,false,true,true,true,true,true,false,false,false,true,true,true,false,true,true,true,false,true,true,true,true,false,true,true,true,true,false,false,false,true,true,true,false,true,false,true,true,true,true,false,false,true,true,true,false,false,true,true,true,true,true,true,true,false,true,false,true,false,false,true,true,true,true,false,false,false,true,true,false,false,false,true,false,true,true,false,true,false,true,true,false,true,false,true,true,true,false,false,false,false,false,false,false,false,false,true,false,true,false,false,false,false,false,true,true,false,false,false,true,false,false,true,false,true,false,true,false,true,true,true,false,false,true,false,false,true,true,false,false,false,true,true,true,true,true,true,false,false,false,false,false,false,true,true,true,true,false,false,true,false,false,true,true,false,true,true,true,true,false,false,true,false,true,true,false,true,false,true,false,false,false,false,false,false,false,false,false,false,true,true,true,false,false,true,true,true,true,false,true,true,true,false,true,false,false,false,false,false,false,false,true,false,false,false,true,true,false,false,true,false,false,true,false,false,true,true,true,false,true,true,false,true,true,true,false,true,true],"repr":"301/601/753/174/120/105/838/323/732/987/504/378/258/474/835/610/412/602/258/765/374/488/169/374/457/845/740/225/153/561/158/677/527/137/827/377/3/778/447/602/65/17/428/887/768/296/312/101/436/358","tolerance":0.005,"cplex_objective":182695.0,"objective":182695,"infeasibility":0,"elapsed_time":0.41900014877319336,"solution_status":"FEASIBLE_POINT","termination_status":"OPTIMAL","gap":0.0033338525430134415}]}}